MANIFEST.in
README.mk
setup.py
mkbok/__init__.py
mkbok/build.py
mkbok.egg-info/PKG-INFO
mkbok.egg-info/SOURCES.txt
mkbok.egg-info/dependency_links.txt
mkbok.egg-info/top_level.txt