Metadata-Version: 1.1
Name: mkbok
Version: 0.0.3
Summary: make markdown ebook
Home-page: https://github.com/larrycai/mkbok
Author: Larry Cai
Author-email: larry.caiyu@gmail.com
License: Apache
Keywords: markdown,ebook,pandoc
Platform: UNKNOWN
Classifier: Development Status :: 3 - Alpha
Classifier: Topic :: Utilities
Classifier: License :: OSI Approved :: Apache Software License
